curl_parsers/__init__.py
curl_parsers/cli.py
curl_parsers/form_data_boundary.py
curl_parsers/generator.py
curl_parsers/parser_curl.py
curl_parsers-0.2.1.dist-info/licenses/LICENSE
curl_parsers-0.2.1.dist-info/METADATA
curl_parsers-0.2.1.dist-info/WHEEL
curl_parsers-0.2.1.dist-info/entry_points.txt
curl_parsers-0.2.1.dist-info/top_level.txt
curl_parsers-0.2.1.dist-info/RECORD
