Metadata-Version: 2.4
Name: curl_parsers
Version: 0.2.1
Summary: Convert curl commands to Python requests code or JSON.
Author-email: 影子 <yxdszlkc@163.com>
License: MIT
Project-URL: Homepage, https://gitee.com/yxdsz/curl_parsers
Project-URL: Repository, https://gitee.com/yxdsz/curl_parsers.git
Project-URL: IssueTracker, https://gitee.com/yxdsz/curl_parsers/issues
Classifier: Programming Language :: Python :: 3
Classifier: License :: OSI Approved :: MIT License
Classifier: Operating System :: OS Independent
Requires-Python: >=3.6
License-File: LICENSE
Dynamic: license-file
